[
    {
        "logo":"../Assets/college.jpeg",
        "link":"https://www.eduvision.edu.pk/edu_news/aps-c-kohat-teaching-jobs-jn-2120",
        "job_title": "APS&C Kohat Teaching Jobs",
        "type": "Private",
        "Sector": "College",
        "Announced": "16-05-2024",
        "Deadline": "27-05-2024"
    },
    {
        "logo":"../Assets/organiztion.jpg",
        "link":"https://www.eduvision.edu.pk/edu_news/balochistan-development-contract-jobs-jn-2121",
        "job_title": "Balochistan Development Contract Jobs",
        "type": "Government",
        "Sector": "Organization",
        "Announced": "16-05-2024",
        "Deadline": "31-05-2024"
    },
    {
        "logo":"../Assets/college.jpeg",
        "link":"https://www.eduvision.edu.pk/edu_news/gomal-medical-college-faculty-admin-jobs-jn-2122",
        "job_title": "Gomal Medical College Faculty & Admin Jobs",
        "type": "Government",
        "Sector": "College",
        "Announced": "16-05-2024",
        "Deadline": "31-05-2024"
    },
    {
        "logo":"../Assets/organiztion.jpg",
        "link":"https://www.eduvision.edu.pk/edu_news/sundar-industrial-estate-lahore-multiple-jobs-jn-2123",
        "job_title": "Sundar Industrial Estate Lahore Multiple Jobs",
        "type": "Private",
        "Sector": "Company",
        "Announced": "16-05-2024",
        "Deadline": "03-06-2024"
    },
    {
        "logo":"../Assets/university.png",
        "link":"https://www.eduvision.edu.pk/edu_news/university-of-sargodha-faculty-jobs-jn-2115",
        "job_title": "University of Sargodha Faculty Jobs",
        "type": "Government",
        "Sector": "University",
        "Announced": "15-05-2024",
        "Deadline": "03-06-2024"
    },
    {
        "logo":"../Assets/army_jobs.jpg",
        "link":"https://www.eduvision.edu.pk/edu_news/military-lands-and-cantonments-lahore-staff-jobs-jn-2116",
        "job_title": "Military Lands and Cantonments Lahore Staff Jobs",
        "type": "Government",
        "Sector": "Army",
        "Announced": "15-05-2024",
        "Deadline": "30-05-2024"
    },
    {
        "logo":"../Assets/Govt-of_Pak.png",
        "link":"https://www.eduvision.edu.pk/edu_news/health-services-muzaffarabad-technician-jobs-jn-2117",
        "job_title": "Health Services Muzaffarabad Technician Jobs",
        "type": "Government",
        "Sector": "Health",
        "Announced": "15-05-2024",
        "Deadline": "30-05-2024"
    },
    {
        "logo":"../Assets/organiztion.jpg",
        "link":"https://www.eduvision.edu.pk/edu_news/faisalabad-electric-supply-company-limited-officer-jobs-jn-2118",
        "job_title": "Faisalabad Electric Supply Company Limited Officer Jobs",
        "type": "Government",
        "Sector": "FESCL",
        "Announced": "15-05-2024",
        "Deadline": "30-05-2024"
    },
    {
        "logo":"../Assets/organiztion.jpg",
        "link":"https://www.eduvision.edu.pk/edu_news/commerce-industry-ajk-staff-jobs-jn-2119",
        "job_title": "Commerce & Industry AJK Staff Jobs",
        "type": "Government",
        "Sector": "Organization",
        "Announced": "15-05-2024",
        "Deadline": "30-05-2024"
    },
    {
        "logo":"../Assets/army_jobs.jpg",
        "link":"https://www.eduvision.edu.pk/edu_news/eme-rawalpindi-multiple-jobs-jn-2099",
        "job_title": "EME Rawalpindi Multiple Jobs",
        "type": "Government",
        "Sector": "Army",
        "Announced": "14-05-2024",
        "Deadline": "27-05-2024"
    },
    {
        "logo":"../Assets/army_jobs.jpg",
        "link":"https://www.eduvision.edu.pk/edu_news/afirm-rawalpindi-staff-jobs-jn-2100",
        "job_title": "AFIRM Rawalpindi Staff Jobs",
        "type": "Government",
        "Sector": "Army",
        "Announced": "14-05-2024",
        "Deadline": "27-05-2024"
    },
    {
        "logo":"../Assets/college.jpeg",
        "link":"https://www.eduvision.edu.pk/edu_news/cadet-college-ghotki-teaching-non-teaching-jobs-jn-2101",
        "job_title": "Cadet College Ghotki Teaching & Non Teaching Jobs",
        "type": "Private",
        "Sector": "College",
        "Announced": "14-05-2024",
        "Deadline": "11-06-2024"
    },
    {
        "logo":"../Assets/college.jpeg",
        "link":"https://www.eduvision.edu.pk/edu_news/continental-medical-college-lahore-faculty-jobs-jn-2102",
        "job_title": "Continental Medical College Lahore Faculty Jobs",
        "type": "Private",
        "Sector": "College",
        "Announced": "14-05-2024",
        "Deadline": "11-06-2024"
    },
    {
        "logo":"../Assets/organiztion.jpg",
        "link":"https://www.eduvision.edu.pk/edu_news/archelogy-museums-department-islambad-admin-staff-jobs-jn-2103",
        "job_title": "Archelogy & Museums Department Islambad Admin & Staff Jobs",
        "type": "Government",
        "Sector": "Organization",
        "Announced": "14-05-2024",
        "Deadline": "27-05-2024"
    },
    {
        "logo":"../Assets/organiztion.jpg",
        "link":"https://www.eduvision.edu.pk/edu_news/fazaia-degree-college-kamra-teaching-non-teaching-jobs-jn-2104",
        "job_title": "Fazaia Degree College Kamra Teaching & Non Teaching Jobs",
        "type": "Government",
        "Sector": "Organization",
        "Announced": "14-05-2024",
        "Deadline": "19-05-2024"
    },
    {
        "logo":"../Assets/university.png",
        "link":"https://www.eduvision.edu.pk/edu_news/sheikh-khalifa-public-school-rahimyar-khan-teachers-jobs-jn-2105",
        "job_title": "LIAS Faisalabad Teaching & Non Teaching Jobs",
        "type": "Private",
        "Sector": "Institute",
        "Announced": "14-05-2024",
        "Deadline": "20-05-2024"
    },
    {
        "logo":"../Assets/organiztion.jpg",
        "link":"https://www.eduvision.edu.pk/edu_news/military-lands-and-cantonment-department-rawalpindi-staff-jobs-jn-2107",
        "job_title": "Military Lands and Cantonment Department Rawalpindi Staff Jobs",
        "type": "Government",
        "Sector": "Organization",
        "Announced": "14-05-2024",
        "Deadline": "01-06-2024"
    },
    {
        "logo":"../Assets/college.jpeg",
        "link":"https://www.eduvision.edu.pk/edu_news/opf-girls-college-rawalpindi-teaching-non-teaching-jobs-jn-2108",
        "job_title": "OPF Girls College Rawalpindi Teaching & Non Teaching Jobs",
        "type": "Private",
        "Sector": "College",
        "Announced": "14-05-2024",
        "Deadline": "19-05-2024"
    },
    {
        "logo":"../Assets/army_jobs.jpg",
        "link":"https://www.eduvision.edu.pk/edu_news/central-ordinance-depo-sargodha-staff-jobs-jn-2109",
        "job_title": "Central Ordinance Depo Sargodha Staff Jobs",
        "type": "Government",
        "Sector": "Army",
        "Announced": "14-05-2024",
        "Deadline": "27-05-2024"
    },
    {
        "logo":"../Assets/organiztion.jpg",
        "link":"https://www.eduvision.edu.pk/edu_news/public-health-punjab-admin-jobs-jn-2110",
        "job_title": "Public Health Punjab Admin Jobs",
        "type": "Government",
        "Sector": "Organization",
        "Announced": "14-05-2024",
        "Deadline": "24-05-2024"
    },
    {
        "logo":"../Assets/university.png",
        "link":"https://www.eduvision.edu.pk/edu_news/uhs-lahore-staff-jobs-jn-2111",
        "job_title": "UHS Lahore Staff Jobs",
        "type": "Government",
        "Sector": "University",
        "Announced": "14-05-2024",
        "Deadline": "04-06-2024"
    }
]